animepipeline/__init__.py
animepipeline/__main__.py
animepipeline/bt/__init__.py
animepipeline/bt/qb.py
animepipeline/cli/README.md
animepipeline/cli/__init__.py
animepipeline/cli/btf/__init__.py
animepipeline/cli/btf/__main__.py
animepipeline/cli/rename/__init__.py
animepipeline/cli/rename/__main__.py
animepipeline/config/__init__.py
animepipeline/config/rss.py
animepipeline/config/server.py
animepipeline/encode/__init__.py
animepipeline/encode/finalrip.py
animepipeline/encode/type.py
animepipeline/loop.py
animepipeline/mediainfo/__init__.py
animepipeline/mediainfo/mediainfo.py
animepipeline/mediainfo/name.py
animepipeline/mediainfo/type.py
animepipeline/pool/__init__.py
animepipeline/pool/task.py
animepipeline/post/__init__.py
animepipeline/post/tg.py
animepipeline/rss/__init__.py
animepipeline/rss/nyaa.py
animepipeline/rss/type.py
animepipeline/store/__init__.py
animepipeline/store/task.py
animepipeline/template/__init__.py
animepipeline/template/bangumi.py
animepipeline/template/mediainfo.py
animepipeline/template/template.py
animepipeline/util/__init__.py
animepipeline/util/bt.py
animepipeline/util/video.py
animepipeline-0.0.6.dist-info/LICENSE
animepipeline-0.0.6.dist-info/METADATA
animepipeline-0.0.6.dist-info/WHEEL
animepipeline-0.0.6.dist-info/entry_points.txt
animepipeline-0.0.6.dist-info/RECORD
