Metadata-Version: 2.1
Name: animepipeline
Version: 0.0.6
Summary: auto encode new anime episode
Home-page: https://github.com/TensoRaws/AnimePipeline
License: MIT
Author: Tohrusky
Requires-Python: >=3.9,<4.0
Classifier: License :: OSI Approved :: MIT License
Classifier: Programming Language :: Python :: 3
Classifier: Programming Language :: Python :: 3.9
Classifier: Programming Language :: Python :: 3.10
Classifier: Programming Language :: Python :: 3.11
Classifier: Programming Language :: Python :: 3.12
Classifier: Programming Language :: Python :: 3.13
Requires-Dist: feedparser (>=6.0.11,<7.0.0)
Requires-Dist: httpx (>=0.28.1,<0.29.0)
Requires-Dist: loguru (>=0.7.3,<0.8.0)
Requires-Dist: pydantic (>=2.10.4,<3.0.0)
Requires-Dist: pymediainfo-tensoraws (==6.1.0)
Requires-Dist: python-telegram-bot (>=21.9,<22.0)
Requires-Dist: pyyaml (>=6.0.2,<7.0.0)
Requires-Dist: qbittorrent-api (>=2024.9.67,<2025.0.0)
Requires-Dist: tenacity (>=9.0.0,<10.0.0)
Requires-Dist: torrentool (>=1.2.0,<2.0.0)
Project-URL: Repository, https://github.com/TensoRaws/AnimePipeline
